keyboard/__init__.py
keyboard/__main__.py
keyboard/_canonical_names.py
keyboard/_darwinkeyboard.py
keyboard/_darwinmouse.py
keyboard/_generic.py
keyboard/_keyboard_event.py
keyboard/_keyboard_tests.py
keyboard/_mouse_event.py
keyboard/_mouse_tests.py
keyboard/_nixcommon.py
keyboard/_nixkeyboard.py
keyboard/_nixmouse.py
keyboard/_winkeyboard.py
keyboard/_winmouse.py
keyboard/mouse.py
keyboard_darwin_fix-0.13.6.dist-info/LICENSE.txt
keyboard_darwin_fix-0.13.6.dist-info/METADATA
keyboard_darwin_fix-0.13.6.dist-info/WHEEL
keyboard_darwin_fix-0.13.6.dist-info/top_level.txt
keyboard_darwin_fix-0.13.6.dist-info/RECORD
