Metadata-Version: 2.2
Name: keyboard-darwin-fix
Version: 0.13.6
Summary: Hook and simulate keyboard events on Windows and Linux
Home-page: https://github.com/kkristof200/keyboard-darwin-fix
Author: kkristof200
Author-email: 
License: MIT
Keywords: keyboard hook simulate hotkey
Classifier: Development Status :: 4 - Beta
Classifier: License :: OSI Approved :: MIT License
Classifier: Operating System :: Microsoft :: Windows
Classifier: Operating System :: Unix
Classifier: Operating System :: MacOS :: MacOS X
Classifier: Programming Language :: Python :: 2
Classifier: Programming Language :: Python :: 3
Classifier: Topic :: Software Development :: Libraries :: Python Modules
Classifier: Topic :: Utilities
License-File: LICENSE.txt
Requires-Dist: pyobjc; sys_platform == "darwin"
Dynamic: author
Dynamic: classifier
Dynamic: description
Dynamic: description-content-type
Dynamic: home-page
Dynamic: keywords
Dynamic: license
Dynamic: requires-dist
Dynamic: summary
